setup.py
sdk/__init__.py
sdk/my_test.py
zhupengfei.eleme.egg-info/PKG-INFO
zhupengfei.eleme.egg-info/SOURCES.txt
zhupengfei.eleme.egg-info/dependency_links.txt
zhupengfei.eleme.egg-info/top_level.txt
zhupengfei.eleme.egg-info/zip-safe