Metadata-Version: 1.1
Name: zhupengfei.eleme
Version: 1.0.0
Summary: this is a test package for packing python liberaries tutorial.
Home-page: UNKNOWN
Author: David
Author-email: pengfei.zhu@ele.me
License: MIT
Keywords: test python package
Platform: UNKNOWN
Classifier: License :: OSI Approved :: MIT License
Classifier: Programming Language :: Python
Classifier: Intended Audience :: Developers
Classifier: Operating System :: OS Independent
